[{"opnSvcNm": "계량기제조업", "opnSvcId": "09_28_03_P", "opnSfTeamCode": "3030000", "mgtNo": "2020303010306500002", "apvPermYmd": "20200218", "apvCancelYmd": null, "trdStateGbn": "01", "trdStateNm": "영업/정상", "dtlStateGbn": "01", "dtlStateNm": "영업중", "dcbYmd": null, "clgStdt": null, "clgEnddt": null, "ropnYmd": null, "siteTel": "0218334903", "siteArea": null, "sitePostNo": null, "siteWhlAddr": "서울특별시 성동구 성수동1가 656번지 1110호 서울숲 L-Tower 1405호", "rdnWhlAddr": "서울특별시 성동구 아차산로 17, 서울숲 L-Tower 1405호 (성수동1가)", "rdnPostNo": "04789", "bplcNm": "주식회사 스타코프", "lastModTs": "20210611170942", "updateGbn": "U", "updateDt": "2021-06-13 02:40:00.0", "uptaeNm": null, "x": "203994.658040173", "y": "449552.049448345", "offTelno": "0218334903", "wrkpTelno": null}, {"opnSvcNm": "계량기제조업", "opnSvcId": "09_28_03_P", "opnSfTeamCode": "5540000", "mgtNo": "2016554012306500001", "apvPermYmd": "20160509", "apvCancelYmd": null, "trdStateGbn": "01", "trdStateNm": "영업/정상", "dtlStateGbn": "01", "dtlStateNm": "영업중", "dcbYmd": null, "clgStdt": null, "clgEnddt": null, "ropnYmd": null, "siteTel": "0215441662", "siteArea": null, "sitePostNo": null, "siteWhlAddr": null, "rdnWhlAddr": "경기도 광주시 오포읍 되치미길 14-26", "rdnPostNo": "12774", "bplcNm": "주식회사 동도엘엠에스", "lastModTs": "20210615141729", "updateGbn": "U", "updateDt": "2021-06-17 02:40:00.0", "uptaeNm": null, "x": "217352", "y": "426861", "offTelno": "0215441662", "wrkpTelno": null}, {"opnSvcNm": "계량기제조업", "opnSvcId": "09_28_03_P", "opnSfTeamCode": "4830000", "mgtNo": "2021483019106500002", "apvPermYmd": "20210623", "apvCancelYmd": null, "trdStateGbn": "01", "trdStateNm": "영업/정상", "dtlStateGbn": "01", "dtlStateNm": "영업중", "dcbYmd": null, "clgStdt": null, "clgEnddt": null, "ropnYmd": null, "siteTel": "0613319813", "siteArea": null, "sitePostNo": null, "siteWhlAddr": "경기도 안양시 동안구 관양동 799 메가밸리", "rdnWhlAddr": "경기도 안양시 동안구 학의로 268, 메가밸리 4층 415호 (관양동)", "rdnPostNo": "14056", "bplcNm": "(주)디엠파워", "lastModTs": "20210623180848", "updateGbn": "I", "updateDt": "2021-06-25 00:22:54.0", "uptaeNm": null, "x": "197069.82356942", "y": "433267.205928793", "offTelno": "0613319813", "wrkpTelno": null}, {"opnSvcNm": "계량기제조업", "opnSvcId": "09_28_03_P", "opnSfTeamCode": "5710000", "mgtNo": "2018571016006500001", "apvPermYmd": "20180123", "apvCancelYmd": null, "trdStateGbn": "01", "trdStateNm": "영업/정상", "dtlStateGbn": "01", "dtlStateNm": "영업중", "dcbYmd": null, "clgStdt": null, "clgEnddt": null, "ropnYmd": null, "siteTel": "043 905 9980", "siteArea": null, "sitePostNo": null, "siteWhlAddr": "충청북도 청주시 흥덕구 오송읍 쌍청리 497번지 19호", "rdnWhlAddr": "충청북도 청주시 흥덕구 오송읍 미호천길 1016", "rdnPostNo": "28157", "bplcNm": "(주)엘엔에스", "lastModTs": "20210617175447", "updateGbn": "I", "updateDt": "2021-06-19 00:22:54.0", "uptaeNm": null, "x": "230626.550823", "y": "348347.102931", "offTelno": "043 905 9980", "wrkpTelno": null}, {"opnSvcNm": "계량기제조업", "opnSvcId": "09_28_03_P", "opnSfTeamCode": "3530000", "mgtNo": "2004353007006500001", "apvPermYmd": "20041230", "apvCancelYmd": null, "trdStateGbn": "01", "trdStateNm": "영업/정상", "dtlStateGbn": "01", "dtlStateNm": "영업중", "dcbYmd": null, "clgStdt": null, "clgEnddt": null, "ropnYmd": null, "siteTel": "032  8163383", "siteArea": null, "sitePostNo": "405821", "siteWhlAddr": "인천광역시 남동구 고잔동 717번지 7호", "rdnWhlAddr": "인천광역시 남동구 남동동로33번길 28-22 (고잔동)", "rdnPostNo": "405821", "bplcNm": "(주)대한가스기기", "lastModTs": "20210609160332", "updateGbn": "I", "updateDt": "2021-06-11 00:22:55.0", "uptaeNm": null, "x": "172678.51957719", "y": "432089.676688248", "offTelno": "032  8163383", "wrkpTelno": null}, {"opnSvcNm": "계량기제조업", "opnSvcId": "09_28_03_P", "opnSfTeamCode": "4040000", "mgtNo": "2021404022806500001", "apvPermYmd": "20210602", "apvCancelYmd": null, "trdStateGbn": "01", "trdStateNm": "영업/정상", "dtlStateGbn": "01", "dtlStateNm": "영업중", "dcbYmd": null, "clgStdt": null, "clgEnddt": null, "ropnYmd": null, "siteTel": "0317920042", "siteArea": null, "sitePostNo": null, "siteWhlAddr": "경기도 하남시 춘궁동 267-2", "rdnWhlAddr": "경기도 하남시 서하남로451번길 70 (춘궁동)", "rdnPostNo": "13016", "bplcNm": "(주)중원파워", "lastModTs": "20210603142755", "updateGbn": "I", "updateDt": "2021-06-05 00:23:05.0", "uptaeNm": null, "x": "216879.895605873", "y": "446899.646868358", "offTelno": "0317920042", "wrkpTelno": null}, {"opnSvcNm": "계량기제조업", "opnSvcId": "09_28_03_P", "opnSfTeamCode": "3360000", "mgtNo": "2021336014506500001", "apvPermYmd": "20210624", "apvCancelYmd": null, "trdStateGbn": "01", "trdStateNm": "영업/정상", "dtlStateGbn": "01", "dtlStateNm": "영업중", "dcbYmd": null, "clgStdt": null, "clgEnddt": null, "ropnYmd": null, "siteTel": "07051170567", "siteArea": null, "sitePostNo": null, "siteWhlAddr": "부산광역시 강서구 화전동 592-4", "rdnWhlAddr": "부산광역시 강서구 화전산단2로134번길 32 (화전동)", "rdnPostNo": "46741", "bplcNm": "신영엔텍(주)", "lastModTs": "20210624170711", "updateGbn": "I", "updateDt": "2021-06-26 00:22:54.0", "uptaeNm": null, "x": "371883.833449281", "y": "179632.074697137", "offTelno": "07051170567", "wrkpTelno": null}, {"opnSvcNm": "계량기제조업", "opnSvcId": "09_28_03_P", "opnSfTeamCode": "3550000", "mgtNo": "2021355012806500001", "apvPermYmd": "20210607", "apvCancelYmd": null, "trdStateGbn": "01", "trdStateNm": "영업/정상", "dtlStateGbn": "01", "dtlStateNm": "영업중", "dcbYmd": null, "clgStdt": null, "clgEnddt": null, "ropnYmd": null, "siteTel": "032 552 1045", "siteArea": null, "sitePostNo": null, "siteWhlAddr": "인천광역시 계양구 서운동 217-4 (주)셀텍월드", "rdnWhlAddr": "인천광역시 계양구 서운산단로2길 17, (주)셀텍월드 (서운동)", "rdnPostNo": "21072", "bplcNm": "엔텍그린 주식회사", "lastModTs": "20210607172143", "updateGbn": "I", "updateDt": "2021-06-09 00:22:55.0", "uptaeNm": null, "x": null, "y": null, "offTelno": "032 552 1045", "wrkpTelno": null}, {"opnSvcNm": "계량기제조업", "opnSvcId": "09_28_03_P", "opnSfTeamCode": "3230000", "mgtNo": "2012323023106500002", "apvPermYmd": "20120309", "apvCancelYmd": null, "trdStateGbn": "01", "trdStateNm": "영업/정상", "dtlStateGbn": "01", "dtlStateNm": "영업중", "dcbYmd": null, "clgStdt": null, "clgEnddt": null, "ropnYmd": null, "siteTel": "000205395228", "siteArea": null, "sitePostNo": null, "siteWhlAddr": "서울특별시 송파구 문정동 632 가든파이브웍스", "rdnWhlAddr": "서울특별시 송파구 충민로 52, 가든파이브웍스 B동 8층 816,817,818,819호 (문정동)", "rdnPostNo": "05839", "bplcNm": "(주)부민더블유엔피", "lastModTs": "20210602143118", "updateGbn": "U", "updateDt": "2021-06-04 02:40:00.0", "uptaeNm": null, "x": "210857.12769000000", "y": "442038.14324700000", "offTelno": "000205395228", "wrkpTelno": null}, {"opnSvcNm": "계량기제조업", "opnSvcId": "09_28_03_P", "opnSfTeamCode": "4070000", "mgtNo": "2016407008806500005", "apvPermYmd": "20160729", "apvCancelYmd": null, "trdStateGbn": "03", "trdStateNm": "폐업", "dtlStateGbn": "03", "dtlStateNm": "폐업", "dcbYmd": "20200706", "clgStdt": null, "clgEnddt": null, "ropnYmd": null, "siteTel": null, "siteArea": null, "sitePostNo": null, "siteWhlAddr": "경기도 이천시 백사면 현방리 329번지 3호", "rdnWhlAddr": "경기도 이천시 백사면 이여로 445", "rdnPostNo": "17312", "bplcNm": "우리저울", "lastModTs": "20210622163051", "updateGbn": "U", "updateDt": "2021-06-24 02:40:00.0", "uptaeNm": null, "x": "242776.139509783", "y": "425766.473736453", "offTelno": null, "wrkpTelno": null}]