[{"opnSvcNm": "무도장업", "opnSvcId": "10_33_01_P", "opnSfTeamCode": "3860000", "mgtNo": "CDFH3301102020000001", "apvPermYmd": "20200826", "apvCancelYmd": null, "trdStateGbn": "03", "trdStateNm": "폐업", "dtlStateGbn": "03", "dtlStateNm": "폐업", "dcbYmd": "20210608", "clgStdt": null, "clgEnddt": null, "ropnYmd": null, "siteTel": null, "siteArea": null, "sitePostNo": null, "siteWhlAddr": "경기도 부천시 원종동 313-10 부천프라자", "rdnWhlAddr": "경기도 부천시 원종로 64, 부천프라자 7층 1호 (원종동)", "rdnPostNo": "14424", "bplcNm": "나드리무도장", "lastModTs": "20210608201505", "updateGbn": "U", "updateDt": "2021-06-10 02:40:00.0", "uptaeNm": null, "x": "182864.109601021", "y": "446854.109066958", "culPhyedCobNm": "무도장업", "puprSeNm": "사립", "insurJnYnCode": "Y", "lderCnt": null, "bdngDngNum": null, "bdngYarea": null, "memCollTotStfNum": null, "drmkCobNm": null, "bupNm": null}, {"opnSvcNm": "무도장업", "opnSvcId": "10_33_01_P", "opnSfTeamCode": "3930000", "mgtNo": "CDFH3301102020000001", "apvPermYmd": "20201124", "apvCancelYmd": null, "trdStateGbn": "01", "trdStateNm": "영업/정상", "dtlStateGbn": "13", "dtlStateNm": "영업중", "dcbYmd": null, "clgStdt": null, "clgEnddt": null, "ropnYmd": null, "siteTel": "031-484-7080", "siteArea": null, "sitePostNo": null, "siteWhlAddr": "경기도 안산시 단원구 고잔동 539-6 유림빌딩", "rdnWhlAddr": "경기도 안산시 단원구 고잔로 122, 유림빌딩 2층 202~206호 (고잔동)", "rdnPostNo": "15361", "bplcNm": "조아조아무도장", "lastModTs": "20210607095500", "updateGbn": "U", "updateDt": "2021-06-09 02:40:00.0", "uptaeNm": null, "x": "185741.5", "y": "424082.345", "culPhyedCobNm": "무도장업", "puprSeNm": "사립", "insurJnYnCode": null, "lderCnt": null, "bdngDngNum": null, "bdngYarea": null, "memCollTotStfNum": null, "drmkCobNm": null, "bupNm": null}]